flamepy/__init__.py
flamepy/client.py
flamepy/frontend_pb2.py
flamepy/frontend_pb2_grpc.py
flamepy/instance.py
flamepy/service.py
flamepy/shim_pb2.py
flamepy/shim_pb2_grpc.py
flamepy/types.py
flamepy/types_pb2.py
flamepy/types_pb2_grpc.py
flamepy-0.5.0.dist-info/licenses/LICENSE
flamepy-0.5.0.dist-info/METADATA
flamepy-0.5.0.dist-info/WHEEL
flamepy-0.5.0.dist-info/top_level.txt
flamepy-0.5.0.dist-info/RECORD
