Metadata-Version: 2.4
Name: flamepy
Version: 0.5.0
Summary: Python SDK for Flame, a distributed system for Agentic AI
Author-email: XFLOPS Authors <support@xflops.io>
Project-URL: Homepage, https://xflops.io
Project-URL: Repository, https://github.com/xflops/flame
Project-URL: Issues, https://github.com/xflops/flame/issues
Keywords: distributed system,agentic ai,flame,sdk
Classifier: Development Status :: 3 - Alpha
Classifier: Intended Audience :: Developers
Classifier: Operating System :: OS Independent
Classifier: Programming Language :: Python :: 3
Classifier: Programming Language :: Python :: 3.8
Classifier: Programming Language :: Python :: 3.9
Classifier: Programming Language :: Python :: 3.10
Classifier: Programming Language :: Python :: 3.11
Requires-Python: >=3.12
License-File: LICENSE
Requires-Dist: grpcio>=1.50.0
Requires-Dist: grpcio-tools>=1.50.0
Requires-Dist: protobuf>=4.21.0
Requires-Dist: pydantic>=2.11.0
Requires-Dist: fastapi>=0.115.0
Requires-Dist: uvicorn>=0.35.0
Requires-Dist: pyyaml>=6.0.0
Provides-Extra: dev
Requires-Dist: pytest>=7.0.0; extra == "dev"
Requires-Dist: pytest-asyncio>=0.21.0; extra == "dev"
Requires-Dist: black>=22.0.0; extra == "dev"
Requires-Dist: isort>=5.0.0; extra == "dev"
Requires-Dist: mypy>=1.0.0; extra == "dev"
Dynamic: license-file
